LICENSE
README.md
setup.py
NlpToolkit_WordSenseDisambiguation.egg-info/PKG-INFO
NlpToolkit_WordSenseDisambiguation.egg-info/SOURCES.txt
NlpToolkit_WordSenseDisambiguation.egg-info/dependency_links.txt
NlpToolkit_WordSenseDisambiguation.egg-info/requires.txt
NlpToolkit_WordSenseDisambiguation.egg-info/top_level.txt
WordSenseDisambiguation/__init__.py
WordSenseDisambiguation/ParseTree/Lesk.py
WordSenseDisambiguation/ParseTree/MostFrequentTreeAutoSemantic.py
WordSenseDisambiguation/ParseTree/RandomTreeAutoSemantic.py
WordSenseDisambiguation/ParseTree/TreeAutoSemantic.py
WordSenseDisambiguation/ParseTree/__init__.py
WordSenseDisambiguation/Sentence/Lesk.py
WordSenseDisambiguation/Sentence/MostFrequentSentenceAutoSemantic.py
WordSenseDisambiguation/Sentence/RandomSentenceAutoSemantic.py
WordSenseDisambiguation/Sentence/SentenceAutoSemantic.py
WordSenseDisambiguation/Sentence/TurkishSentenceAutoSemantic.py
WordSenseDisambiguation/Sentence/__init__.py