Metadata-Version: 2.1
Name: NlpToolkit-WordSenseDisambiguation
Version: 1.0.3
Summary: Word Sense Disambiguation Library
Home-page: https://github.com/StarlangSoftware/WordSenseDisambiguation-Py
Author: olcaytaner
Author-email: olcay.yildiz@ozyegin.edu.tr
License: UNKNOWN
Platform: UNKNOWN
License-File: LICENSE
